[{"id":"7","sku":"L000007","title":"Collection","type":"collections","link":"http:\/\/www.backcountry.com\/collection\/dinner-with-a-view","author":"shayshay_1792","caption":"Breadwinner #homemade #travelfood","author_image":"http:\/\/content.backcountry.com\/promo_upload\/bcs\/2016\/35853\/img\/profile-shayshay_1792.jpg","images":[{"angle":"Front","url":"http:\/\/content.backcountry.com\/promo_upload\/bcs\/2016\/35853\/img\/ch4-insta3.jpg"},{"angle":"Back","url":"http:\/\/content.backcountry.com\/promo_upload\/bcs\/2016\/35853\/img\/ch4-insta3.jpg"}],"skus":[{"sku":"CCF000P","colorway":"ONECOL","included":"0","brand":"Camp Chef","title":"All-Purpose 5 Piece Chef's Set","price":"33.45","image":"http:\/\/content.backcountry.com\/images\/items\/900\/CCF\/CCF000P\/ONECOL.jpg","options":["One Size"],"swatches":["white"]},{"sku":"CCF001A","colorway":"REG","included":"0","brand":"Camp Chef","title":"Deluxe 9 1\/3-Quart Dutch Oven","price":"70.95","image":"http:\/\/content.backcountry.com\/images\/items\/900\/CCF\/CCF001A\/REG.jpg","options":["One Size"],"swatches":["white"]},{"sku":"GSI002F","colorway":"GN","included":"0","brand":"GSI Outdoors","title":"Pioneer Cutlery","price":"29.95","image":"http:\/\/content.backcountry.com\/images\/items\/large\/GSI\/GSI002F\/GN.jpg","options":["One Size"],"swatches":["green"]},{"sku":"SNO001U","colorway":"ONECOL","included":"0","brand":"Snow Peak","title":"Tableware Set L Family","price":"149.95","image":"http:\/\/content.backcountry.com\/images\/items\/900\/SNO\/SNO001U\/ONECOL.jpg","options":["One Size"],"swatches":["white"]}]}]